setup.py
mueddi_vbar.egg-info/PKG-INFO
mueddi_vbar.egg-info/SOURCES.txt
mueddi_vbar.egg-info/dependency_links.txt
mueddi_vbar.egg-info/top_level.txt
mueddit/__init__.py
mueddit/dawg.c
mueddit/dawg.py
mueddit/leven.c
mueddit/leven.py
mueddit/mueddi.py
mueddit/struct_hash.c
mueddit/struct_hash.py
mueddit/tests/__init__.py
mueddit/tests/test.py